{"is_source_file": false, "format": "", "description": "", "external_files": [], "external_methods": [], "published": [], "classes": [], "methods": [], "calls": [], "search-terms": [], "state": 2, "file_id": 12, "knowledge_revision": 21, "git_revision": "55c739b561f0e3f8d8a8fc5ff7c971c88a486bb8", "hash": "ebece526bc2eadd78ddd787a76c56607", "format-version": 4, "code-base-name": "notes_frontend", "filename": "notes_frontend/README.md", "revision_history": [{"21": "55c739b561f0e3f8d8a8fc5ff7c971c88a486bb8"}]}